Metadata-Version: 2.1
Name: multi_file_exis
Version: 0.0.3
Summary: allows to make a json file in a network folder
Home-page: 
Author: Vincent Welter
Author-email: vincent.welter@outlook.de
License: MIT
Keywords: json
Classifier: Development Status :: 5 - Production/Stable
Classifier: Intended Audience :: Education
Classifier: Operating System :: Microsoft :: Windows :: Windows 11
Classifier: License :: OSI Approved :: MIT License
Classifier: Programming Language :: Python :: 3
License-File: LICENCE.txt
Requires-Dist: json
Requires-Dist: os
